Metadata-Version: 1.0
Name: distribution-fun
Version: 0.1
Summary: Gaussian and Binomial distributions
Home-page: UNKNOWN
Author: Jarmila Ruzicka
Author-email: UNKNOWN
License: UNKNOWN
Platform: UNKNOWN
